LICENSE
MANIFEST.in
README.rst
setup.py
helga_urbandictionary/__init__.py
helga_urbandictionary/plugin.py
helga_urbandictionary.egg-info/PKG-INFO
helga_urbandictionary.egg-info/SOURCES.txt
helga_urbandictionary.egg-info/dependency_links.txt
helga_urbandictionary.egg-info/entry_points.txt
helga_urbandictionary.egg-info/requires.txt
helga_urbandictionary.egg-info/top_level.txt
helga_urbandictionary.egg-info/zip-safe