Metadata-Version: 1.1
Name: helga-urbandictionary
Version: 2.0.0
Summary: looks up definitions for words on urban dictionary
Home-page: https://github.com/michaelorr/helga-urbandictionary
Author: Michael Orr
Author-email: michael@orr.co
License: LICENSE
Keywords: irc bot urbandictionary
Platform: UNKNOWN
Classifier: Development Status :: 4 - Beta
Classifier: Topic :: Communications :: Chat :: Internet Relay Chat
Classifier: License :: OSI Approved :: GNU General Public License v3 (GPLv3)
Classifier: Operating System :: OS Independent
Classifier: Programming Language :: Python
Classifier: Topic :: Software Development :: Libraries :: Python Modules
Classifier: Topic :: Communications :: Chat :: Internet Relay Chat
